Metadata-Version: 2.1
Name: number-spacy
Version: 0.0.1
Summary: A spaCy extension for enhanced number entity recognition and extraction as structured data.
Home-page: https://github.com/wjbmattingly/number-spacy
Author: WJB Mattingly
Classifier: Programming Language :: Python
Classifier: Programming Language :: Python :: 3
Classifier: License :: OSI Approved :: MIT License
Classifier: Operating System :: OS Independent
